{
  "posts": [
    {
      "text": "test",
      "files": [
        {},
        {},
        {}
      ],
      "id": 1
    },
    {
      "text": "test",
      "files": [
        {},
        {},
        {}
      ],
      "id": 2
    },
    {
      "text": "test",
      "files": [
        {},
        {},
        {}
      ],
      "id": 3
    },
    {
      "text": "test",
      "files": [
        {},
        {},
        {}
      ],
      "id": 4
    },
    {
      "text": "test",
      "files": [
        {},
        {},
        {}
      ],
      "id": 5
    },
    {
      "text": "test",
      "files": [
        {},
        {}
      ],
      "id": 6
    },
    {
      "text": "test",
      "files": [
        {},
        {}
      ],
      "id": 7
    },
    {
      "text": "test",
      "files": [
        {},
        {},
        {}
      ],
      "id": 8
    }
  ],
  "comments": []
}